{
  "version": "6",
  "dialect": "sqlite",
  "id": "6b4ccbe1-db32-4d52-89ff-118ce905ed46",
  "prevId": "6cffba6c-de75-4ac1-8bde-3a882dfdf399",
  "tables": {
    "payments": {
      "name": "payments",
      "columns": {
        "id": {
          "name": "id",
          "type": "integer",
          "primaryKey": true,
          "notNull": true,
          "autoincrement": true
        },
        "uuid": {
          "name": "uuid",
          "type": "text",
          "primaryKey": false,
          "notNull": true,
          "autoincrement": false
        },
        "domain": {
          "name": "domain",
          "type": "text",
          "primaryKey": false,
          "notNull": true,
          "autoincrement": false
        },
        "paymentId": {
          "name": "paymentId",
          "type": "text",
          "primaryKey": false,
          "notNull": true,
          "autoincrement": false
        },
        "paymentInfo": {
          "name": "paymentInfo",
          "type": "text",
          "primaryKey": false,
          "notNull": true,
          "autoincrement": false
        },
        "planInfo": {
          "name": "planInfo",
          "type": "text",
          "primaryKey": false,
          "notNull": true,
          "autoincrement": false
        },
        "isTrial": {
          "name": "isTrial",
          "type": "integer",
          "primaryKey": false,
          "notNull": true,
          "autoincrement": false
        },
        "paymentExpiry": {
          "name": "paymentExpiry",
          "type": "integer",
          "primaryKey": false,
          "notNull": true,
          "autoincrement": false
        },
        "expiresAt": {
          "name": "expiresAt",
          "type": "integer",
          "primaryKey": false,
          "notNull": true,
          "autoincrement": false
        },
        "createdAt": {
          "name": "createdAt",
          "type": "integer",
          "primaryKey": false,
          "notNull": true,
          "autoincrement": false
        },
        "updatedAt": {
          "name": "updatedAt",
          "type": "integer",
          "primaryKey": false,
          "notNull": true,
          "autoincrement": false
        }
      },
      "indexes": {
        "payments_uuid_unique": {
          "name": "payments_uuid_unique",
          "columns": [
            "uuid"
          ],
          "isUnique": true
        },
        "payments_paymentId_unique": {
          "name": "payments_paymentId_unique",
          "columns": [
            "paymentId"
          ],
          "isUnique": true
        },
        "index_domain": {
          "name": "index_domain",
          "columns": [
            "domain"
          ],
          "isUnique": false
        },
        "index_paymentId": {
          "name": "index_paymentId",
          "columns": [
            "paymentId"
          ],
          "isUnique": false
        }
      },
      "foreignKeys": {},
      "compositePrimaryKeys": {},
      "uniqueConstraints": {},
      "checkConstraints": {}
    },
    "subscriptions": {
      "name": "subscriptions",
      "columns": {
        "uuid": {
          "name": "uuid",
          "type": "text",
          "primaryKey": true,
          "notNull": true,
          "autoincrement": false
        },
        "domain": {
          "name": "domain",
          "type": "text",
          "primaryKey": false,
          "notNull": true,
          "autoincrement": false
        },
        "paymentId": {
          "name": "paymentId",
          "type": "integer",
          "primaryKey": false,
          "notNull": true,
          "autoincrement": false
        },
        "expiresAt": {
          "name": "expiresAt",
          "type": "integer",
          "primaryKey": false,
          "notNull": true,
          "autoincrement": false
        },
        "createdAt": {
          "name": "createdAt",
          "type": "integer",
          "primaryKey": false,
          "notNull": true,
          "autoincrement": false
        },
        "updatedAt": {
          "name": "updatedAt",
          "type": "integer",
          "primaryKey": false,
          "notNull": true,
          "autoincrement": false
        }
      },
      "indexes": {
        "subscriptions_uuid_unique": {
          "name": "subscriptions_uuid_unique",
          "columns": [
            "uuid"
          ],
          "isUnique": true
        },
        "name": {
          "name": "name",
          "columns": [
            "domain"
          ],
          "isUnique": false
        }
      },
      "foreignKeys": {
        "subscriptions_paymentId_payments_id_fk": {
          "name": "subscriptions_paymentId_payments_id_fk",
          "tableFrom": "subscriptions",
          "tableTo": "payments",
          "columnsFrom": [
            "paymentId"
          ],
          "columnsTo": [
            "id"
          ],
          "onDelete": "no action",
          "onUpdate": "no action"
        }
      },
      "compositePrimaryKeys": {},
      "uniqueConstraints": {},
      "checkConstraints": {}
    }
  },
  "views": {},
  "enums": {},
  "_meta": {
    "schemas": {},
    "tables": {},
    "columns": {}
  },
  "internal": {
    "indexes": {}
  }
}